odoo10_addon_base_external_dbsource_sqlite-10.0.1.0.0-py2.7-nspkg.pth
odoo10_addon_base_external_dbsource_sqlite-10.0.1.0.0.dist-info/top_level.txt
odoo10_addon_base_external_dbsource_sqlite-10.0.1.0.0.dist-info/WHEEL
odoo10_addon_base_external_dbsource_sqlite-10.0.1.0.0.dist-info/RECORD
odoo10_addon_base_external_dbsource_sqlite-10.0.1.0.0.dist-info/metadata.json
odoo10_addon_base_external_dbsource_sqlite-10.0.1.0.0.dist-info/DESCRIPTION.rst
odoo10_addon_base_external_dbsource_sqlite-10.0.1.0.0.dist-info/METADATA
odoo10_addon_base_external_dbsource_sqlite-10.0.1.0.0.dist-info/namespace_packages.txt
odoo/addons/base_external_dbsource_sqlite/__manifest__.py
odoo/addons/base_external_dbsource_sqlite/__init__.py
odoo/addons/base_external_dbsource_sqlite/README.rst
odoo/addons/base_external_dbsource_sqlite/models/__init__.py
odoo/addons/base_external_dbsource_sqlite/models/base_external_dbsource.py
odoo/addons/base_external_dbsource_sqlite/tests/test_base_external_dbsource.py
odoo/addons/base_external_dbsource_sqlite/tests/__init__.py
odoo/addons/base_external_dbsource_sqlite/demo/base_external_dbsource.xml
