Metadata-Version: 2.0
Name: odoo10-addon-base-external-dbsource-sqlite
Version: 10.0.1.0.0
Summary: External Database Source - SQLite
Home-page: https://github.com/OCA/server-tools
Author: Daniel Reis, LasLabs, Odoo Community Association (OCA)
Author-email: support@odoo-community.org
License: LGPL-3
Platform: UNKNOWN
Requires-Dist: odoo (<10.1dev,>=10.0)
Requires-Dist: odoo10-addon-base-external-dbsource
Classifier: Programming Language :: Python :: 2.7
Classifier: Framework :: Odoo
Classifier: License :: OSI Approved :: GNU Lesser General Public License v3 (LGPLv3)
